labonneboite_common/__init__.py
labonneboite_common/chunk.py
labonneboite_common/departements.py
labonneboite_common/encoding.py
labonneboite_common/models/__init__.py
labonneboite_common/models/office_mixin.py
labonneboite_common/py.typed
labonneboite_common/siret.py
labonneboite_common/tests/__init__.py
labonneboite_common/tests/chunk_test.py
labonneboite_common/tests/departements_test.py
labonneboite_common/tests/encoding_test.py
labonneboite_common/tests/siret_test.py
labonneboite_common-0.5.3.dist-info/LICENSE
labonneboite_common-0.5.3.dist-info/WHEEL
labonneboite_common-0.5.3.dist-info/METADATA
labonneboite_common-0.5.3.dist-info/RECORD
